zerocv/__init__.py
zerocv/fps.py
zerocv/utils.py
zerocv/video.py
zerocv/cv/__init__.py
zerocv/cv/face_detector.py
zerocv/dlib/__init__.py
zerocv/dlib/facial_recognition.py
zerocv/ext/ColorModule.py
zerocv/ext/HandTrackingModule.py
zerocv/ext/__init__.py
zerocv/mp/__init__.py
zerocv/mp/face_detector.py
zerocv/mp/face_mesh.py
zerocv/mp/hands_detector.py
zerocv/mp/holistic_detector.py
zerocv/mp/pose_detector.py
zerocv/mp/selfie_segmentator.py
zerocv/tm/__init__.py
zerocv/tm/model.py
zerocv/yolo3/__init__.py
zerocv/yolo3/object_detector.py
zerocv-0.0.5.dist-info/LICENSE.txt
zerocv-0.0.5.dist-info/METADATA
zerocv-0.0.5.dist-info/WHEEL
zerocv-0.0.5.dist-info/top_level.txt
zerocv-0.0.5.dist-info/RECORD
